Metadata-Version: 1.0
Name: printListModuleAm
Version: 1.0.0
Summary: An API to print the given List input
Home-page: UNKNOWN
Author: Ameermon v A
Author-email: UNKNOWN
License: UNKNOWN
Platform: UNKNOWN
